explog/__init__.py
explog/logger.py
explog-0.0.3.dist-info/LICENSE
explog-0.0.3.dist-info/METADATA
explog-0.0.3.dist-info/WHEEL
explog-0.0.3.dist-info/top_level.txt
explog-0.0.3.dist-info/RECORD
