Metadata-Version: 2.1
Name: explog
Version: 0.0.3
Summary: Experiment Logger
Author-email: Gaspard Lambrechts <gsprd@protonmail.com>
Project-URL: Homepage, https://github.com/glambrechts/explog
Project-URL: Issues, https://github.com/glambrechts/explog/issues
Classifier: Programming Language :: Python :: 3
Classifier: License :: OSI Approved :: MIT License
Classifier: Operating System :: OS Independent
Requires-Python: >=3.8
License-File: LICENSE
Requires-Dist: pandas
